impala/__init__.py
impala/physics/__init__.py
impala/physics/physical_models_vec.py
impala/superCal/__init__.py
impala/superCal/impala_clust.py
impala/superCal/impala_noProbit_emu.py
impala/superCal/map.py
impala/superCal/models_withLik.py
impala/superCal/pbar.py
impala/superCal/plots.py
impala/superCal/post_process.py
impala_calib-0.6.0.dist-info/licenses/LICENSE
impala_calib-0.6.0.dist-info/METADATA
impala_calib-0.6.0.dist-info/WHEEL
impala_calib-0.6.0.dist-info/top_level.txt
impala_calib-0.6.0.dist-info/RECORD
