Metadata-Version: 2.4
Name: impala-calib
Version: 0.6.0
Summary: Bayesian model calibration
Author-email: Devin Francom <dfrancom@lanl.gov>
License-Expression: BSD-3-Clause
Requires-Python: >=3.10
License-File: LICENSE
Requires-Dist: matplotlib>=3.7.3
Requires-Dist: numpy>=1.24.4
Requires-Dist: scipy>=1.10.1
Requires-Dist: seaborn>=0.13.2
Provides-Extra: numba
Requires-Dist: numba>=0.62.1; extra == "numba"
Dynamic: license-file
